Workbook

Sheet Project Overview
A1: Property Operations & Maintenance — Financial Analysis Workbook
A2: Portfolio project | Operations + Vendor Management + Maintenance Spend + Savings Opportunities
A4: Objective
A5: Use six months of synthetic maintenance expense data to analyze spend by property, maintenance type, service category and vendor; identify budget leakage; quantify modeled savings opportunities; and connect the financial story to the Notion + Make property-operations workflow.
A9: Key Financial Outputs
A10: Metric | B10: Value | D10: Sheet | E10: Purpose
A11: Total Actual Spend ($) | B11: =Analysis!B4 -> 570780 | D11: Maintenance Spend Data | E11: Transaction-level dataset with linked master data and formula-driven savings estimates.
A12: Potential Savings ($) | B12: =Analysis!H4 -> 34245.1 | D12: Analysis | E12: KPIs plus spend analysis by property, maintenance type, category and vendor.
A13: Annualized Savings ($) | B13: =Analysis!B6 -> 68490.2 | D13: Savings Opportunities | E13: Modeled savings by driver and vendor, with recommended management actions.
D14: Vendor Master | E14: Vendor attributes aligned to the Notion portfolio database.
D15: Property Master | E15: Property attributes and annual maintenance budgets aligned to the Notion portfolio database.
D16: Assumptions | E16: Editable savings rates and analysis period assumptions.
A18: How to Work With This Workbook
A19: Step | B19: Action
A20: 1 | B20: Review the blue-font inputs in Maintenance Spend Data. Formula cells should not be overwritten.
A21: 2 | B21: Use the dropdowns to change property, vendor, maintenance type, invoice status, or savings driver.
A22: 3 | B22: Adjust the yellow savings-rate assumptions to stress-test the opportunity model.
A23: 4 | B23: Use Analysis to explain where spend is concentrated and where cost leakage appears.
A24: 5 | B24: Use Savings Opportunities to build an executive recommendation: what to address first, why, and estimated financial impact.
A26: Financial Model Color Convention
A27: Color | B27: Meaning
A28: Blue font | B28: Hardcoded / editable inputs
A29: Green font | B29: Links to another worksheet
A30: Yellow fill | B30: Key assumptions to review / change
A32: Disclosure: This workbook is a portfolio demonstration using synthetic maintenance expenses. Property and vendor master records are aligned to the fictional Notion property-operations project. Savings percentages are scenario assumptions, not guaranteed realized savings.

Sheet Maintenance Spend Data
A1: Expense ID | B1: Expense Date | C1: Expense Month | D1: Property ID | E1: Property Name | F1: Property Type | G1: Vendor | H1: Service Category | I1: Preferred Vendor | J1: Vendor Rating | K1: Maintenance Type | L1: Priority | M1: Budgeted Cost ($) | N1: Actual Cost ($) | O1: Variance ($) | P1: Variance % | Q1: Preventable Emergency? | R1: Invoice Status | S1: Savings Driver | T1: Savings Rate | U1: Potential Savings ($) | V1: Net Cost After Savings ($) | W1: Annualized Savings Run-Rate ($) | X1: Notes
A2: EXP-001 | B2: 46045 | C2: =DATE(YEAR(B2),MONTH(B2),1) -> 46023 | D2: 1 | E2: =IFERROR(VLOOKUP(D2,'Property Master'!$A$2:$J$7,2,FALSE),"") -> Lakeview Residences | F2: =IFERROR(VLOOKUP(D2,'Property Master'!$A$2:$J$7,3,FALSE),"") -> Multifamily | G2: BlueSky HVAC Services | H2: =IFERROR(VLOOKUP(G2,'Vendor Master'!$A$2:$H$11,2,FALSE),"") -> HVAC | I2: =IFERROR(VLOOKUP(G2,'Vendor Master'!$A$2:$H$11,3,FALSE),"") -> Yes | J2: =IFERROR(VLOOKUP(G2,'Vendor Master'!$A$2:$H$11,4,FALSE),0) -> 4.8 | K2: Preventive | L2: Medium | M2: 10700 | N2: 9770 | O2: =M2-N2 -> 930 | P2: =IFERROR(O2/M2,0) -> 0.086915888 | Q2: N/A | R2: Paid | S2: None | T2: =IFERROR(VLOOKUP(S2,Assumptions!$A$7:$B$12,2,FALSE),0) -> 0 | U2: =N2*T2 -> 0 | V2: =N2-U2 -> 9770 | W2: =U2*12/Assumptions!$B$4 -> 0 | X2: Routine spend; no immediate savings action identified.
A3: EXP-002 | B3: 46079 | C3: =DATE(YEAR(B3),MONTH(B3),1) -> 46054 | D3: 1 | E3: =IFERROR(VLOOKUP(D3,'Property Master'!$A$2:$J$7,2,FALSE),"") -> Lakeview Residences | F3: =IFERROR(VLOOKUP(D3,'Property Master'!$A$2:$J$7,3,FALSE),"") -> Multifamily | G3: ClearPath Janitorial | H3: =IFERROR(VLOOKUP(G3,'Vendor Master'!$A$2:$H$11,2,FALSE),"") -> Cleaning | I3: =IFERROR(VLOOKUP(G3,'Vendor Master'!$A$2:$H$11,3,FALSE),"") -> No | J3: =IFERROR(VLOOKUP(G3,'Vendor Master'!$A$2:$H$11,4,FALSE),0) -> 4.1 | K3: Preventive | L3: Medium | M3: 2400 | N3: 2170 | O3: =M3-N3 -> 230 | P3: =IFERROR(O3/M3,0) -> 0.095833333 | Q3: N/A | R3: Paid | S3: Non-Preferred Vendor | T3: =IFERROR(VLOOKUP(S3,Assumptions!$A$7:$B$12,2,FALSE),0) -> 0.08 | U3: =N3*T3 -> 173.6 | V3: =N3-U3 -> 1996.4 | W3: =U3*12/Assumptions!$B$4 -> 347.2 | X3: Non-preferred vendor spend; review sourcing or negotiated rates.
A4: EXP-003 | B4: 46103 | C4: =DATE(YEAR(B4),MONTH(B4),1) -> 46082 | D4: 1 | E4: =IFERROR(VLOOKUP(D4,'Property Master'!$A$2:$J$7,2,FALSE),"") -> Lakeview Residences | F4: =IFERROR(VLOOKUP(D4,'Property Master'!$A$2:$J$7,3,FALSE),"") -> Multifamily | G4: BlueSky HVAC Services | H4: =IFERROR(VLOOKUP(G4,'Vendor Master'!$A$2:$H$11,2,FALSE),"") -> HVAC | I4: =IFERROR(VLOOKUP(G4,'Vendor Master'!$A$2:$H$11,3,FALSE),"") -> Yes | J4: =IFERROR(VLOOKUP(G4,'Vendor Master'!$A$2:$H$11,4,FALSE),0) -> 4.8 | K4: Corrective | L4: High | M4: 10300 | N4: 11790 | O4: =M4-N4 -> -1490 | P4: =IFERROR(O4/M4,0) -> -0.14466019 | Q4: N/A | R4: Approved | S4: None | T4: =IFERROR(VLOOKUP(S4,Assumptions!$A$7:$B$12,2,FALSE),0) -> 0 | U4: =N4*T4 -> 0 | V4: =N4-U4 -> 11790 | W4: =U4*12/Assumptions!$B$4 -> 0 | X4: Routine spend; no immediate savings action identified.
A5: EXP-004 | B5: 46115 | C5: =DATE(YEAR(B5),MONTH(B5),1) -> 46113 | D5: 1 | E5: =IFERROR(VLOOKUP(D5,'Property Master'!$A$2:$J$7,2,FALSE),"") -> Lakeview Residences | F5: =IFERROR(VLOOKUP(D5,'Property Master'!$A$2:$J$7,3,FALSE),"") -> Multifamily | G5: AllPro Building Services | H5: =IFERROR(VLOOKUP(G5,'Vendor Master'!$A$2:$H$11,2,FALSE),"") -> General Contractor | I5: =IFERROR(VLOOKUP(G5,'Vendor Master'!$A$2:$H$11,3,FALSE),"") -> Yes | J5: =IFERROR(VLOOKUP(G5,'Vendor Master'!$A$2:$H$11,4,FALSE),0) -> 4.3 | K5: Corrective | L5: High | M5: 14800 | N5: 14820 | O5: =M5-N5 -> -20 | P5: =IFERROR(O5/M5,0) -> -0.0013513514 | Q5: N/A | R5: Pending | S5: None | T5: =IFERROR(VLOOKUP(S5,Assumptions!$A$7:$B$12,2,FALSE),0) -> 0 | U5: =N5*T5 -> 0 | V5: =N5-U5 -> 14820 | W5: =U5*12/Assumptions!$B$4 -> 0 | X5: Routine spend; no immediate savings action identified.
A6: EXP-005 | B6: 46155 | C6: =DATE(YEAR(B6),MONTH(B6),1) -> 46143 | D6: 1 | E6: =IFERROR(VLOOKUP(D6,'Property Master'!$A$2:$J$7,2,FALSE),"") -> Lakeview Residences | F6: =IFERROR(VLOOKUP(D6,'Property Master'!$A$2:$J$7,3,FALSE),"") -> Multifamily | G6: BlueSky HVAC Services | H6: =IFERROR(VLOOKUP(G6,'Vendor Master'!$A$2:$H$11,2,FALSE),"") -> HVAC | I6: =IFERROR(VLOOKUP(G6,'Vendor Master'!$A$2:$H$11,3,FALSE),"") -> Yes | J6: =IFERROR(VLOOKUP(G6,'Vendor Master'!$A$2:$H$11,4,FALSE),0) -> 4.8 | K6: Preventive | L6: Medium | M6: 12400 | N6: 11940 | O6: =M6-N6 -> 460 | P6: =IFERROR(O6/M6,0) -> 0.037096774 | Q6: N/A | R6: Paid | S6: None | T6: =IFERROR(VLOOKUP(S6,Assumptions!$A$7:$B$12,2,FALSE),0) -> 0 | U6: =N6*T6 -> 0 | V6: =N6-U6 -> 11940 | W6: =U6*12/Assumptions!$B$4 -> 0 | X6: Routine spend; no immediate savings action identified.
A7: EXP-006 | B7: 46177 | C7: =DATE(YEAR(B7),MONTH(B7),1) -> 46174 | D7: 1 | E7: =IFERROR(VLOOKUP(D7,'Property Master'!$A$2:$J$7,2,FALSE),"") -> Lakeview Residences | F7: =IFERROR(VLOOKUP(D7,'Property Master'!$A$2:$J$7,3,FALSE),"") -> Multifamily | G7: SafeGuard Fire Systems | H7: =IFERROR(VLOOKUP(G7,'Vendor Master'!$A$2:$H$11,2,FALSE),"") -> Fire & Life Safety | I7: =IFERROR(VLOOKUP(G7,'Vendor Master'!$A$2:$H$11,3,FALSE),"") -> Yes | J7: =IFERROR(VLOOKUP(G7,'Vendor Master'!$A$2:$H$11,4,FALSE),0) -> 4.9 | K7: Corrective | L7: High | M7: 4200 | N7: 4400 | O7: =M7-N7 -> -200 | P7: =IFERROR(O7/M7,0) -> -0.047619048 | Q7: N/A | R7: Approved | S7: None | T7: =IFERROR(VLOOKUP(S7,Assumptions!$A$7:$B$12,2,FALSE),0) -> 0 | U7: =N7*T7 -> 0 | V7: =N7-U7 -> 4400 | W7: =U7*12/Assumptions!$B$4 -> 0 | X7: Routine spend; no immediate savings action identified.
A8: EXP-007 | B8: 46036 | C8: =DATE(YEAR(B8),MONTH(B8),1) -> 46023 | D8: 1 | E8: =IFERROR(VLOOKUP(D8,'Property Master'!$A$2:$J$7,2,FALSE),"") -> Lakeview Residences | F8: =IFERROR(VLOOKUP(D8,'Property Master'!$A$2:$J$7,3,FALSE),"") -> Multifamily | G8: Summit Roofing Group | H8: =IFERROR(VLOOKUP(G8,'Vendor Master'!$A$2:$H$11,2,FALSE),"") -> Roofing | I8: =IFERROR(VLOOKUP(G8,'Vendor Master'!$A$2:$H$11,3,FALSE),"") -> No | J8: =IFERROR(VLOOKUP(G8,'Vendor Master'!$A$2:$H$11,4,FALSE),0) -> 4.2 | K8: Preventive | L8: Medium | M8: 10000 | N8: 9350 | O8: =M8-N8 -> 650 | P8: =IFERROR(O8/M8,0) -> 0.065 | Q8: N/A | R8: Paid | S8: Non-Preferred Vendor | T8: =IFERROR(VLOOKUP(S8,Assumptions!$A$7:$B$12,2,FALSE),0) -> 0.08 | U8: =N8*T8 -> 748 | V8: =N8-U8 -> 8602 | W8: =U8*12/Assumptions!$B$4 -> 1496 | X8: Non-preferred vendor spend; review sourcing or negotiated rates.
A9: EXP-008 | B9: 46058 | C9: =DATE(YEAR(B9),MONTH(B9),1) -> 46054 | D9: 1 | E9: =IFERROR(VLOOKUP(D9,'Property Master'!$A$2:$J$7,2,FALSE),"") -> Lakeview Residences | F9: =IFERROR(VLOOKUP(D9,'Property Master'!$A$2:$J$7,3,FALSE),"") -> Multifamily | G9: Evergreen Grounds | H9: =IFERROR(VLOOKUP(G9,'Vendor Master'!$A$2:$H$11,2,FALSE),"") -> Landscaping | I9: =IFERROR(VLOOKUP(G9,'Vendor Master'!$A$2:$H$11,3,FALSE),"") -> Yes | J9: =IFERROR(VLOOKUP(G9,'Vendor Master'!$A$2:$H$11,4,FALSE),0) -> 4.5 | K9: Emergency | L9: Critical | M9: 4300 | N9: 5800 | O9: =M9-N9 -> -1500 | P9: =IFERROR(O9/M9,0) -> -0.34883721 | Q9: Yes | R9: Paid | S9: Preventable Emergency | T9: =IFERROR(VLOOKUP(S9,Assumptions!$A$7:$B$12,2,FALSE),0) -> 0.2 | U9: =N9*T9 -> 1160 | V9: =N9-U9 -> 4640 | W9: =U9*12/Assumptions!$B$4 -> 2320 | X9: Emergency event potentially avoidable through stronger PM cadence.
A10: EXP-009 | B10: 46090 | C10: =DATE(YEAR(B10),MONTH(B10),1) -> 46082 | D10: 1 | E10: =IFERROR(VLOOKUP(D10,'Property Master'!$A$2:$J$7,2,FALSE),"") -> Lakeview Residences | F10: =IFERROR(VLOOKUP(D10,'Property Master'!$A$2:$J$7,3,FALSE),"") -> Multifamily | G10: ClearPath Janitorial | H10: =IFERROR(VLOOKUP(G10,'Vendor Master'!$A$2:$H$11,2,FALSE),"") -> Cleaning | I10: =IFERROR(VLOOKUP(G10,'Vendor Master'!$A$2:$H$11,3,FALSE),"") -> No | J10: =IFERROR(VLOOKUP(G10,'Vendor Master'!$A$2:$H$11,4,FALSE),0) -> 4.1 | K10: Corrective | L10: Medium | M10: 6000 | N10: 6040 | O10: =M10-N10 -> -40 | P10: =IFERROR(O10/M10,0) -> -0.0066666667 | Q10: N/A | R10: Approved | S10: Non-Preferred Vendor | T10: =IFERROR(VLOOKUP(S10,Assumptions!$A$7:$B$12,2,FALSE),0) -> 0.08 | U10: =N10*T10 -> 483.2 | V10: =N10-U10 -> 5556.8 | W10: =U10*12/Assumptions!$B$4 -> 966.4 | X10: Non-preferred vendor spend; review sourcing or negotiated rates.
A11: EXP-010 | B11: 46030 | C11: =DATE(YEAR(B11),MONTH(B11),1) -> 46023 | D11: 2 | E11: =IFERROR(VLOOKUP(D11,'Property Master'!$A$2:$J$7,2,FALSE),"") -> Cypress Office Center | F11: =IFERROR(VLOOKUP(D11,'Property Master'!$A$2:$J$7,3,FALSE),"") -> Office | G11: SafeGuard Fire Systems | H11: =IFERROR(VLOOKUP(G11,'Vendor Master'!$A$2:$H$11,2,FALSE),"") -> Fire & Life Safety | I11: =IFERROR(VLOOKUP(G11,'Vendor Master'!$A$2:$H$11,3,FALSE),"") -> Yes | J11: =IFERROR(VLOOKUP(G11,'Vendor Master'!$A$2:$H$11,4,FALSE),0) -> 4.9 | K11: Corrective | L11: Medium | M11: 10000 | N11: 12280 | O11: =M11-N11 -> -2280 | P11: =IFERROR(O11/M11,0) -> -0.228 | Q11: N/A | R11: Approved | S11: Budget Overrun Review | T11: =IFERROR(VLOOKUP(S11,Assumptions!$A$7:$B$12,2,FALSE),0) -> 0.06 | U11: =N11*T11 -> 736.8 | V11: =N11-U11 -> 11543.2 | W11: =U11*12/Assumptions!$B$4 -> 1473.6 | X11: Actual cost materially exceeded the approved estimate.
A12: EXP-011 | B12: 46063 | C12: =DATE(YEAR(B12),MONTH(B12),1) -> 46054 | D12: 2 | E12: =IFERROR(VLOOKUP(D12,'Property Master'!$A$2:$J$7,2,FALSE),"") -> Cypress Office Center | F12: =IFERROR(VLOOKUP(D12,'Property Master'!$A$2:$J$7,3,FALSE),"") -> Office | G12: RapidFlow Plumbing | H12: =IFERROR(VLOOKUP(G12,'Vendor Master'!$A$2:$H$11,2,FALSE),"") -> Plumbing | I12: =IFERROR(VLOOKUP(G12,'Vendor Master'!$A$2:$H$11,3,FALSE),"") -> Yes | J12: =IFERROR(VLOOKUP(G12,'Vendor Master'!$A$2:$H$11,4,FALSE),0) -> 4.6 | K12: Preventive | L12: Medium | M12: 8100 | N12: 7260 | O12: =M12-N12 -> 840 | P12: =IFERROR(O12/M12,0) -> 0.1037037 | Q12: N/A | R12: Pending | S12: None | T12: =IFERROR(VLOOKUP(S12,Assumptions!$A$7:$B$12,2,FALSE),0) -> 0 | U12: =N12*T12 -> 0 | V12: =N12-U12 -> 7260 | W12: =U12*12/Assumptions!$B$4 -> 0 | X12: Routine spend; no immediate savings action identified.
A13: EXP-012 | B13: 46102 | C13: =DATE(YEAR(B13),MONTH(B13),1) -> 46082 | D13: 2 | E13: =IFERROR(VLOOKUP(D13,'Property Master'!$A$2:$J$7,2,FALSE),"") -> Cypress Office Center | F13: =IFERROR(VLOOKUP(D13,'Property Master'!$A$2:$J$7,3,FALSE),"") -> Office | G13: AllPro Building Services | H13: =IFERROR(VLOOKUP(G13,'Vendor Master'!$A$2:$H$11,2,FALSE),"") -> General Contractor | I13: =IFERROR(VLOOKUP(G13,'Vendor Master'!$A$2:$H$11,3,FALSE),"") -> Yes | J13: =IFERROR(VLOOKUP(G13,'Vendor Master'!$A$2:$H$11,4,FALSE),0) -> 4.3 | K13: Preventive | L13: Medium | M13: 15900 | N13: 17480 | O13: =M13-N13 -> -1580 | P13: =IFERROR(O13/M13,0) -> -0.099371069 | Q13: N/A | R13: Paid | S13: Preventive Optimization | T13: =IFERROR(VLOOKUP(S13,Assumptions!$A$7:$B$12,2,FALSE),0) -> 0.1 | U13: =N13*T13 -> 1748 | V13: =N13-U13 -> 15732 | W13: =U13*12/Assumptions!$B$4 -> 3496 | X13: Review PM scope/frequency for cost-efficiency.
... A55: EXP-054 | B55: 46097 | C55: =DATE(YEAR(B55),MONTH(B55),1) -> 46082 | D55: 6 | E55: =IFERROR(VLOOKUP(D55,'Property Master'!$A$2:$J$7,2,FALSE),"") -> Pinecrest Business Park | F55: =IFERROR(VLOOKUP(D55,'Property Master'!$A$2:$J$7,3,FALSE),"") -> Office | G55: AllPro Building Services | H55: =IFERROR(VLOOKUP(G55,'Vendor Master'!$A$2:$H$11,2,FALSE),"") -> General Contractor | I55: =IFERROR(VLOOKUP(G55,'Vendor Master'!$A$2:$H$11,3,FALSE),"") -> Yes | J55: =IFERROR(VLOOKUP(G55,'Vendor Master'!$A$2:$H$11,4,FALSE),0) -> 4.3 | K55: Corrective | L55: High | M55: 16700 | N55: 21290 | O55: =M55-N55 -> -4590 | P55: =IFERROR(O55/M55,0) -> -0.2748503 | Q55: N/A | R55: Paid | S55: Budget Overrun Review | T55: =IFERROR(VLOOKUP(S55,Assumptions!$A$7:$B$12,2,FALSE),0) -> 0.06 | U55: =N55*T55 -> 1277.4 | V55: =N55-U55 -> 20012.6 | W55: =U55*12/Assumptions!$B$4 -> 2554.8 | X55: Actual cost materially exceeded the approved estimate.

Sheet Analysis
A1: Property Maintenance Spend & Savings Analysis
A2: Financial analysis of maintenance spend, budget variance, vendor usage, emergency costs, and modeled savings opportunities | Jan–Jun 2026
A4: Total Actual Spend ($) | B4: =SUM('Maintenance Spend Data'!$N$2:$N$55) -> 570780 | C4: Quoted / Budgeted Spend ($) | D4: =SUM('Maintenance Spend Data'!$M$2:$M$55) -> 528700 | E4: Transaction Variance ($) | F4: =SUM('Maintenance Spend Data'!$O$2:$O$55) -> -42080 | G4: Potential Savings ($) | H4: =SUM('Maintenance Spend Data'!$U$2:$U$55) -> 34245.1
A6: Annualized Savings ($) | B6: =SUM('Maintenance Spend Data'!$W$2:$W$55) -> 68490.2 | C6: Emergency Spend % | D6: =IFERROR(SUMIF('Maintenance Spend Data'!$K$2:$K$55,"Emergency",'Maintenance Spend Data'!$N$2:$N$55)/B4,0) -> 0.11249518 | E6: Preferred Vendor Usage % | F6: =IFERROR(COUNTIF('Maintenance Spend Data'!$I$2:$I$55,"Yes")/COUNTA('Maintenance Spend Data'!$A$2:$A$55),0) -> 0.77777778 | G6: Preventive Spend % | H6: =IFERROR(SUMIF('Maintenance Spend Data'!$K$2:$K$55,"Preventive",'Maintenance Spend Data'!$N$2:$N$55)/B4,0) -> 0.51305231
A9: Spend by Property
A10: Property Name | B10: Annual Budget ($) | C10: 6-Mo Prorated Budget ($) | D10: Actual Spend ($) | E10: Variance vs Prorated ($) | F10: Potential Savings ($) | G10: Spend % of Prorated
A11: Lakeview Residences | B11: =IFERROR(VLOOKUP(A11,'Property Master'!$B$2:$H$7,7,FALSE),0) -> 285000 | C11: =B11*Assumptions!$B$4/12 -> 142500 | D11: =SUMIF('Maintenance Spend Data'!$E$2:$E$55,A11,'Maintenance Spend Data'!$N$2:$N$55) -> 76080 | E11: =C11-D11 -> 66420 | F11: =SUMIF('Maintenance Spend Data'!$E$2:$E$55,A11,'Maintenance Spend Data'!$U$2:$U$55) -> 2564.8 | G11: =IFERROR(D11/C11,0) -> 0.53389474
A12: Cypress Office Center | B12: =IFERROR(VLOOKUP(A12,'Property Master'!$B$2:$H$7,7,FALSE),0) -> 196000 | C12: =B12*Assumptions!$B$4/12 -> 98000 | D12: =SUMIF('Maintenance Spend Data'!$E$2:$E$55,A12,'Maintenance Spend Data'!$N$2:$N$55) -> 94100 | E12: =C12-D12 -> 3900 | F12: =SUMIF('Maintenance Spend Data'!$E$2:$E$55,A12,'Maintenance Spend Data'!$U$2:$U$55) -> 8017.6 | G12: =IFERROR(D12/C12,0) -> 0.96020408
A13: Sunset Retail Plaza | B13: =IFERROR(VLOOKUP(A13,'Property Master'!$B$2:$H$7,7,FALSE),0) -> 172000 | C13: =B13*Assumptions!$B$4/12 -> 86000 | D13: =SUMIF('Maintenance Spend Data'!$E$2:$E$55,A13,'Maintenance Spend Data'!$N$2:$N$55) -> 83430 | E13: =C13-D13 -> 2570 | F13: =SUMIF('Maintenance Spend Data'!$E$2:$E$55,A13,'Maintenance Spend Data'!$U$2:$U$55) -> 3852.8 | G13: =IFERROR(D13/C13,0) -> 0.97011628
A14: Harbor Point Apartments | B14: =IFERROR(VLOOKUP(A14,'Property Master'!$B$2:$H$7,7,FALSE),0) -> 348000 | C14: =B14*Assumptions!$B$4/12 -> 174000 | D14: =SUMIF('Maintenance Spend Data'!$E$2:$E$55,A14,'Maintenance Spend Data'!$N$2:$N$55) -> 92200 | E14: =C14-D14 -> 81800 | F14: =SUMIF('Maintenance Spend Data'!$E$2:$E$55,A14,'Maintenance Spend Data'!$U$2:$U$55) -> 4435.5 | G14: =IFERROR(D14/C14,0) -> 0.52988506
A15: Magnolia Mixed Use | B15: =IFERROR(VLOOKUP(A15,'Property Master'!$B$2:$H$7,7,FALSE),0) -> 238000 | C15: =B15*Assumptions!$B$4/12 -> 119000 | D15: =SUMIF('Maintenance Spend Data'!$E$2:$E$55,A15,'Maintenance Spend Data'!$N$2:$N$55) -> 88170 | E15: =C15-D15 -> 30830 | F15: =SUMIF('Maintenance Spend Data'!$E$2:$E$55,A15,'Maintenance Spend Data'!$U$2:$U$55) -> 7219.2 | G15: =IFERROR(D15/C15,0) -> 0.74092437
A16: Pinecrest Business Park | B16: =IFERROR(VLOOKUP(A16,'Property Master'!$B$2:$H$7,7,FALSE),0) -> 214000 | C16: =B16*Assumptions!$B$4/12 -> 107000 | D16: =SUMIF('Maintenance Spend Data'!$E$2:$E$55,A16,'Maintenance Spend Data'!$N$2:$N$55) -> 136800 | E16: =C16-D16 -> -29800 | F16: =SUMIF('Maintenance Spend Data'!$E$2:$E$55,A16,'Maintenance Spend Data'!$U$2:$U$55) -> 8155.2 | G16: =IFERROR(D16/C16,0) -> 1.2785047
A20: Spend by Maintenance Type | F20: Spend by Service Category
A21: Maintenance Type | B21: Actual Spend ($) | C21: Potential Savings ($) | D21: Share of Spend | F21: Service Category | G21: Actual Spend ($) | H21: Potential Savings ($) | I21: Savings % of Spend
A22: Preventive | B22: =SUMIF('Maintenance Spend Data'!$K$2:$K$55,A22,'Maintenance Spend Data'!$N$2:$N$55) -> 292840 | C22: =SUMIF('Maintenance Spend Data'!$K$2:$K$55,A22,'Maintenance Spend Data'!$U$2:$U$55) -> 12763.7 | D22: =IFERROR(B22/$B$4,0) -> 0.51305231 | F22: General Contractor | G22: =SUMIF('Maintenance Spend Data'!$H$2:$H$55,F22,'Maintenance Spend Data'!$N$2:$N$55) -> 136130 | H22: =SUMIF('Maintenance Spend Data'!$H$2:$H$55,F22,'Maintenance Spend Data'!$U$2:$U$55) -> 7489.2 | I22: =IFERROR(H22/G22,0) -> 0.055015059
A23: Corrective | B23: =SUMIF('Maintenance Spend Data'!$K$2:$K$55,A23,'Maintenance Spend Data'!$N$2:$N$55) -> 213730 | C23: =SUMIF('Maintenance Spend Data'!$K$2:$K$55,A23,'Maintenance Spend Data'!$U$2:$U$55) -> 10462.2 | D23: =IFERROR(B23/$B$4,0) -> 0.3744525 | F23: HVAC | G23: =SUMIF('Maintenance Spend Data'!$H$2:$H$55,F23,'Maintenance Spend Data'!$N$2:$N$55) -> 95130 | H23: =SUMIF('Maintenance Spend Data'!$H$2:$H$55,F23,'Maintenance Spend Data'!$U$2:$U$55) -> 2599.8 | I23: =IFERROR(H23/G23,0) -> 0.027328918
A24: Emergency | B24: =SUMIF('Maintenance Spend Data'!$K$2:$K$55,A24,'Maintenance Spend Data'!$N$2:$N$55) -> 64210 | C24: =SUMIF('Maintenance Spend Data'!$K$2:$K$55,A24,'Maintenance Spend Data'!$U$2:$U$55) -> 11019.2 | D24: =IFERROR(B24/$B$4,0) -> 0.11249518 | F24: Cleaning | G24: =SUMIF('Maintenance Spend Data'!$H$2:$H$55,F24,'Maintenance Spend Data'!$N$2:$N$55) -> 58480 | H24: =SUMIF('Maintenance Spend Data'!$H$2:$H$55,F24,'Maintenance Spend Data'!$U$2:$U$55) -> 6041.6 | I24: =IFERROR(H24/G24,0) -> 0.10331053
F25: Landscaping | G25: =SUMIF('Maintenance Spend Data'!$H$2:$H$55,F25,'Maintenance Spend Data'!$N$2:$N$55) -> 37820 | H25: =SUMIF('Maintenance Spend Data'!$H$2:$H$55,F25,'Maintenance Spend Data'!$U$2:$U$55) -> 2720.5 | I25: =IFERROR(H25/G25,0) -> 0.07193284
F26: Elevator | G26: =SUMIF('Maintenance Spend Data'!$H$2:$H$55,F26,'Maintenance Spend Data'!$N$2:$N$55) -> 39870 | H26: =SUMIF('Maintenance Spend Data'!$H$2:$H$55,F26,'Maintenance Spend Data'!$U$2:$U$55) -> 3924.6 | I26: =IFERROR(H26/G26,0) -> 0.098434913
F27: Plumbing | G27: =SUMIF('Maintenance Spend Data'!$H$2:$H$55,F27,'Maintenance Spend Data'!$N$2:$N$55) -> 31910 | H27: =SUMIF('Maintenance Spend Data'!$H$2:$H$55,F27,'Maintenance Spend Data'!$U$2:$U$55) -> 0 | I27: =IFERROR(H27/G27,0) -> 0
A28: Vendor Spend & Opportunity | F28: Fire & Life Safety | G28: =SUMIF('Maintenance Spend Data'!$H$2:$H$55,F28,'Maintenance Spend Data'!$N$2:$N$55) -> 34900 | H28: =SUMIF('Maintenance Spend Data'!$H$2:$H$55,F28,'Maintenance Spend Data'!$U$2:$U$55) -> 1518 | I28: =IFERROR(H28/G28,0) -> 0.043495702
A29: Vendor | B29: Preferred? | C29: Actual Spend ($) | D29: Potential Savings ($) | E29: Rating | F29: Pest Control | G29: =SUMIF('Maintenance Spend Data'!$H$2:$H$55,F29,'Maintenance Spend Data'!$N$2:$N$55) -> 6300 | H29: =SUMIF('Maintenance Spend Data'!$H$2:$H$55,F29,'Maintenance Spend Data'!$U$2:$U$55) -> 88 | I29: =IFERROR(H29/G29,0) -> 0.013968254
A30: AllPro Building Services | B30: =IFERROR(VLOOKUP(A30,'Vendor Master'!$A$2:$D$11,3,FALSE),"") -> Yes | C30: =SUMIF('Maintenance Spend Data'!$G$2:$G$55,A30,'Maintenance Spend Data'!$N$2:$N$55) -> 136130 | D30: =SUMIF('Maintenance Spend Data'!$G$2:$G$55,A30,'Maintenance Spend Data'!$U$2:$U$55) -> 7489.2 | E30: =IFERROR(VLOOKUP(A30,'Vendor Master'!$A$2:$D$11,4,FALSE),0) -> 4.3 | F30: Roofing | G30: =SUMIF('Maintenance Spend Data'!$H$2:$H$55,F30,'Maintenance Spend Data'!$N$2:$N$55) -> 34590 | H30: =SUMIF('Maintenance Spend Data'!$H$2:$H$55,F30,'Maintenance Spend Data'!$U$2:$U$55) -> 2767.2 | I30: =IFERROR(H30/G30,0) -> 0.08
A31: BlueSky HVAC Services | B31: =IFERROR(VLOOKUP(A31,'Vendor Master'!$A$2:$D$11,3,FALSE),"") -> Yes | C31: =SUMIF('Maintenance Spend Data'!$G$2:$G$55,A31,'Maintenance Spend Data'!$N$2:$N$55) -> 95130 | D31: =SUMIF('Maintenance Spend Data'!$G$2:$G$55,A31,'Maintenance Spend Data'!$U$2:$U$55) -> 2599.8 | E31: =IFERROR(VLOOKUP(A31,'Vendor Master'!$A$2:$D$11,4,FALSE),0) -> 4.8 | F31: Electrical | G31: =SUMIF('Maintenance Spend Data'!$H$2:$H$55,F31,'Maintenance Spend Data'!$N$2:$N$55) -> 95650 | H31: =SUMIF('Maintenance Spend Data'!$H$2:$H$55,F31,'Maintenance Spend Data'!$U$2:$U$55) -> 7096.2 | I31: =IFERROR(H31/G31,0) -> 0.074189232
A32: ClearPath Janitorial | B32: =IFERROR(VLOOKUP(A32,'Vendor Master'!$A$2:$D$11,3,FALSE),"") -> No | C32: =SUMIF('Maintenance Spend Data'!$G$2:$G$55,A32,'Maintenance Spend Data'!$N$2:$N$55) -> 58480 | D32: =SUMIF('Maintenance Spend Data'!$G$2:$G$55,A32,'Maintenance Spend Data'!$U$2:$U$55) -> 6041.6 | E32: =IFERROR(VLOOKUP(A32,'Vendor Master'!$A$2:$D$11,4,FALSE),0) -> 4.1
A33: Evergreen Grounds | B33: =IFERROR(VLOOKUP(A33,'Vendor Master'!$A$2:$D$11,3,FALSE),"") -> Yes | C33: =SUMIF('Maintenance Spend Data'!$G$2:$G$55,A33,'Maintenance Spend Data'!$N$2:$N$55) -> 37820 | D33: =SUMIF('Maintenance Spend Data'!$G$2:$G$55,A33,'Maintenance Spend Data'!$U$2:$U$55) -> 2720.5 | E33: =IFERROR(VLOOKUP(A33,'Vendor Master'!$A$2:$D$11,4,FALSE),0) -> 4.5
A34: PrimeLift Elevator Co. | B34: =IFERROR(VLOOKUP(A34,'Vendor Master'!$A$2:$D$11,3,FALSE),"") -> Yes | C34: =SUMIF('Maintenance Spend Data'!$G$2:$G$55,A34,'Maintenance Spend Data'!$N$2:$N$55) -> 39870 | D34: =SUMIF('Maintenance Spend Data'!$G$2:$G$55,A34,'Maintenance Spend Data'!$U$2:$U$55) -> 3924.6 | E34: =IFERROR(VLOOKUP(A34,'Vendor Master'!$A$2:$D$11,4,FALSE),0) -> 4.4
A35: RapidFlow Plumbing | B35: =IFERROR(VLOOKUP(A35,'Vendor Master'!$A$2:$D$11,3,FALSE),"") -> Yes | C35: =SUMIF('Maintenance Spend Data'!$G$2:$G$55,A35,'Maintenance Spend Data'!$N$2:$N$55) -> 31910 | D35: =SUMIF('Maintenance Spend Data'!$G$2:$G$55,A35,'Maintenance Spend Data'!$U$2:$U$55) -> 0 | E35: =IFERROR(VLOOKUP(A35,'Vendor Master'!$A$2:$D$11,4,FALSE),0) -> 4.6
A36: SafeGuard Fire Systems | B36: =IFERROR(VLOOKUP(A36,'Vendor Master'!$A$2:$D$11,3,FALSE),"") -> Yes | C36: =SUMIF('Maintenance Spend Data'!$G$2:$G$55,A36,'Maintenance Spend Data'!$N$2:$N$55) -> 34900 | D36: =SUMIF('Maintenance Spend Data'!$G$2:$G$55,A36,'Maintenance Spend Data'!$U$2:$U$55) -> 1518 | E36: =IFERROR(VLOOKUP(A36,'Vendor Master'!$A$2:$D$11,4,FALSE),0) -> 4.9
A37: Shield Pest Solutions | B37: =IFERROR(VLOOKUP(A37,'Vendor Master'!$A$2:$D$11,3,FALSE),"") -> Yes | C37: =SUMIF('Maintenance Spend Data'!$G$2:$G$55,A37,'Maintenance Spend Data'!$N$2:$N$55) -> 6300 | D37: =SUMIF('Maintenance Spend Data'!$G$2:$G$55,A37,'Maintenance Spend Data'!$U$2:$U$55) -> 88 | E37: =IFERROR(VLOOKUP(A37,'Vendor Master'!$A$2:$D$11,4,FALSE),0) -> 4.6
A38: Summit Roofing Group | B38: =IFERROR(VLOOKUP(A38,'Vendor Master'!$A$2:$D$11,3,FALSE),"") -> No | C38: =SUMIF('Maintenance Spend Data'!$G$2:$G$55,A38,'Maintenance Spend Data'!$N$2:$N$55) -> 34590 | D38: =SUMIF('Maintenance Spend Data'!$G$2:$G$55,A38,'Maintenance Spend Data'!$U$2:$U$55) -> 2767.2 | E38: =IFERROR(VLOOKUP(A38,'Vendor Master'!$A$2:$D$11,4,FALSE),0) -> 4.2
A39: VoltPro Electrical | B39: =IFERROR(VLOOKUP(A39,'Vendor Master'!$A$2:$D$11,3,FALSE),"") -> Yes | C39: =SUMIF('Maintenance Spend Data'!$G$2:$G$55,A39,'Maintenance Spend Data'!$N$2:$N$55) -> 95650 | D39: =SUMIF('Maintenance Spend Data'!$G$2:$G$55,A39,'Maintenance Spend Data'!$U$2:$U$55) -> 7096.2 | E39: =IFERROR(VLOOKUP(A39,'Vendor Master'!$A$2:$D$11,4,FALSE),0) -> 4.7

Sheet Savings Opportunities
A1: Savings Opportunities
A2: Modeled opportunities are scenario estimates for portfolio analysis—not realized savings. Adjust rates in Assumptions to stress-test the opportunity.
A4: Total Potential Savings ($) | B4: =SUM('Maintenance Spend Data'!$U$2:$U$55) -> 34245.1 | C4: Annualized Savings ($) | D4: =SUM('Maintenance Spend Data'!$W$2:$W$55) -> 68490.2 | E4: Savings as % of Spend | F4: =IFERROR(B4/Analysis!$B$4,0) -> 0.059997022
A7: Opportunity by Savings Driver
A8: Savings Driver | B8: Affected Spend ($) | C8: Potential Savings ($) | D8: Annualized Savings ($) | E8: # Transactions | F8: Recommended Action
A9: Preventable Emergency | B9: =SUMIF('Maintenance Spend Data'!$S$2:$S$55,A9,'Maintenance Spend Data'!$N$2:$N$55) -> 51190 | C9: =SUMIF('Maintenance Spend Data'!$S$2:$S$55,A9,'Maintenance Spend Data'!$U$2:$U$55) -> 10238 | D9: =SUMIF('Maintenance Spend Data'!$S$2:$S$55,A9,'Maintenance Spend Data'!$W$2:$W$55) -> 20476 | E9: =COUNTIF('Maintenance Spend Data'!$S$2:$S$55,A9) -> 6 | F9: Strengthen PM cadence and root-cause review for repeat emergency assets.
A10: Non-Preferred Vendor | B10: =SUMIF('Maintenance Spend Data'!$S$2:$S$55,A10,'Maintenance Spend Data'!$N$2:$N$55) -> 81710 | C10: =SUMIF('Maintenance Spend Data'!$S$2:$S$55,A10,'Maintenance Spend Data'!$U$2:$U$55) -> 6536.8 | D10: =SUMIF('Maintenance Spend Data'!$S$2:$S$55,A10,'Maintenance Spend Data'!$W$2:$W$55) -> 13073.6 | E10: =COUNTIF('Maintenance Spend Data'!$S$2:$S$55,A10) -> 10 | F10: Move repeat spend to preferred vendors or renegotiate rate cards.
A11: Vendor Consolidation | B11: =SUMIF('Maintenance Spend Data'!$S$2:$S$55,A11,'Maintenance Spend Data'!$N$2:$N$55) -> 22410 | C11: =SUMIF('Maintenance Spend Data'!$S$2:$S$55,A11,'Maintenance Spend Data'!$U$2:$U$55) -> 1120.5 | D11: =SUMIF('Maintenance Spend Data'!$S$2:$S$55,A11,'Maintenance Spend Data'!$W$2:$W$55) -> 2241 | E11: =COUNTIF('Maintenance Spend Data'!$S$2:$S$55,A11) -> 4 | F11: Bundle recurring services across properties and negotiate portfolio pricing.
A12: Preventive Optimization | B12: =SUMIF('Maintenance Spend Data'!$S$2:$S$55,A12,'Maintenance Spend Data'!$N$2:$N$55) -> 70960 | C12: =SUMIF('Maintenance Spend Data'!$S$2:$S$55,A12,'Maintenance Spend Data'!$U$2:$U$55) -> 7096 | D12: =SUMIF('Maintenance Spend Data'!$S$2:$S$55,A12,'Maintenance Spend Data'!$W$2:$W$55) -> 14192 | E12: =COUNTIF('Maintenance Spend Data'!$S$2:$S$55,A12) -> 4 | F12: Review PM scope/frequency and eliminate low-value repeat work.
A13: Budget Overrun Review | B13: =SUMIF('Maintenance Spend Data'!$S$2:$S$55,A13,'Maintenance Spend Data'!$N$2:$N$55) -> 154230 | C13: =SUMIF('Maintenance Spend Data'!$S$2:$S$55,A13,'Maintenance Spend Data'!$U$2:$U$55) -> 9253.8 | D13: =SUMIF('Maintenance Spend Data'!$S$2:$S$55,A13,'Maintenance Spend Data'!$W$2:$W$55) -> 18507.6 | E13: =COUNTIF('Maintenance Spend Data'!$S$2:$S$55,A13) -> 10 | F13: Investigate quote-to-invoice leakage and approval controls.
A14: None | B14: =SUMIF('Maintenance Spend Data'!$S$2:$S$55,A14,'Maintenance Spend Data'!$N$2:$N$55) -> 190280 | C14: =SUMIF('Maintenance Spend Data'!$S$2:$S$55,A14,'Maintenance Spend Data'!$U$2:$U$55) -> 0 | D14: =SUMIF('Maintenance Spend Data'!$S$2:$S$55,A14,'Maintenance Spend Data'!$W$2:$W$55) -> 0 | E14: =COUNTIF('Maintenance Spend Data'!$S$2:$S$55,A14) -> 20 | F14: Maintain current controls; no quantified action assigned.
A17: Vendor-Level Opportunity Review
A18: Vendor | B18: Preferred? | C18: Actual Spend ($) | D18: Potential Savings ($) | E18: Rating | F18: Review Focus
A19: AllPro Building Services | B19: =IFERROR(VLOOKUP(A19,'Vendor Master'!$A$2:$D$11,3,FALSE),"") -> Yes | C19: =SUMIF('Maintenance Spend Data'!$G$2:$G$55,A19,'Maintenance Spend Data'!$N$2:$N$55) -> 136130 | D19: =SUMIF('Maintenance Spend Data'!$G$2:$G$55,A19,'Maintenance Spend Data'!$U$2:$U$55) -> 7489.2 | E19: =IFERROR(VLOOKUP(A19,'Vendor Master'!$A$2:$D$11,4,FALSE),0) -> 4.3 | F19: Preferred vendor with moderate rating: review service quality and contract value.
A20: BlueSky HVAC Services | B20: =IFERROR(VLOOKUP(A20,'Vendor Master'!$A$2:$D$11,3,FALSE),"") -> Yes | C20: =SUMIF('Maintenance Spend Data'!$G$2:$G$55,A20,'Maintenance Spend Data'!$N$2:$N$55) -> 95130 | D20: =SUMIF('Maintenance Spend Data'!$G$2:$G$55,A20,'Maintenance Spend Data'!$U$2:$U$55) -> 2599.8 | E20: =IFERROR(VLOOKUP(A20,'Vendor Master'!$A$2:$D$11,4,FALSE),0) -> 4.8 | F20: Maintain preferred relationship; monitor cost and service performance.
A21: ClearPath Janitorial | B21: =IFERROR(VLOOKUP(A21,'Vendor Master'!$A$2:$D$11,3,FALSE),"") -> No | C21: =SUMIF('Maintenance Spend Data'!$G$2:$G$55,A21,'Maintenance Spend Data'!$N$2:$N$55) -> 58480 | D21: =SUMIF('Maintenance Spend Data'!$G$2:$G$55,A21,'Maintenance Spend Data'!$U$2:$U$55) -> 6041.6 | E21: =IFERROR(VLOOKUP(A21,'Vendor Master'!$A$2:$D$11,4,FALSE),0) -> 4.1 | F21: Non-preferred vendor: review sourcing, pricing, and conversion to preferred status.
A22: Evergreen Grounds | B22: =IFERROR(VLOOKUP(A22,'Vendor Master'!$A$2:$D$11,3,FALSE),"") -> Yes | C22: =SUMIF('Maintenance Spend Data'!$G$2:$G$55,A22,'Maintenance Spend Data'!$N$2:$N$55) -> 37820 | D22: =SUMIF('Maintenance Spend Data'!$G$2:$G$55,A22,'Maintenance Spend Data'!$U$2:$U$55) -> 2720.5 | E22: =IFERROR(VLOOKUP(A22,'Vendor Master'!$A$2:$D$11,4,FALSE),0) -> 4.5 | F22: Maintain preferred relationship; monitor cost and service performance.
A23: PrimeLift Elevator Co. | B23: =IFERROR(VLOOKUP(A23,'Vendor Master'!$A$2:$D$11,3,FALSE),"") -> Yes | C23: =SUMIF('Maintenance Spend Data'!$G$2:$G$55,A23,'Maintenance Spend Data'!$N$2:$N$55) -> 39870 | D23: =SUMIF('Maintenance Spend Data'!$G$2:$G$55,A23,'Maintenance Spend Data'!$U$2:$U$55) -> 3924.6 | E23: =IFERROR(VLOOKUP(A23,'Vendor Master'!$A$2:$D$11,4,FALSE),0) -> 4.4 | F23: Preferred vendor with moderate rating: review service quality and contract value.
A24: RapidFlow Plumbing | B24: =IFERROR(VLOOKUP(A24,'Vendor Master'!$A$2:$D$11,3,FALSE),"") -> Yes | C24: =SUMIF('Maintenance Spend Data'!$G$2:$G$55,A24,'Maintenance Spend Data'!$N$2:$N$55) -> 31910 | D24: =SUMIF('Maintenance Spend Data'!$G$2:$G$55,A24,'Maintenance Spend Data'!$U$2:$U$55) -> 0 | E24: =IFERROR(VLOOKUP(A24,'Vendor Master'!$A$2:$D$11,4,FALSE),0) -> 4.6 | F24: Maintain preferred relationship; monitor cost and service performance.
A25: SafeGuard Fire Systems | B25: =IFERROR(VLOOKUP(A25,'Vendor Master'!$A$2:$D$11,3,FALSE),"") -> Yes | C25: =SUMIF('Maintenance Spend Data'!$G$2:$G$55,A25,'Maintenance Spend Data'!$N$2:$N$55) -> 34900 | D25: =SUMIF('Maintenance Spend Data'!$G$2:$G$55,A25,'Maintenance Spend Data'!$U$2:$U$55) -> 1518 | E25: =IFERROR(VLOOKUP(A25,'Vendor Master'!$A$2:$D$11,4,FALSE),0) -> 4.9 | F25: Maintain preferred relationship; monitor cost and service performance.
A26: Shield Pest Solutions | B26: =IFERROR(VLOOKUP(A26,'Vendor Master'!$A$2:$D$11,3,FALSE),"") -> Yes | C26: =SUMIF('Maintenance Spend Data'!$G$2:$G$55,A26,'Maintenance Spend Data'!$N$2:$N$55) -> 6300 | D26: =SUMIF('Maintenance Spend Data'!$G$2:$G$55,A26,'Maintenance Spend Data'!$U$2:$U$55) -> 88 | E26: =IFERROR(VLOOKUP(A26,'Vendor Master'!$A$2:$D$11,4,FALSE),0) -> 4.6 | F26: Maintain preferred relationship; monitor cost and service performance.
A27: Summit Roofing Group | B27: =IFERROR(VLOOKUP(A27,'Vendor Master'!$A$2:$D$11,3,FALSE),"") -> No | C27: =SUMIF('Maintenance Spend Data'!$G$2:$G$55,A27,'Maintenance Spend Data'!$N$2:$N$55) -> 34590 | D27: =SUMIF('Maintenance Spend Data'!$G$2:$G$55,A27,'Maintenance Spend Data'!$U$2:$U$55) -> 2767.2 | E27: =IFERROR(VLOOKUP(A27,'Vendor Master'!$A$2:$D$11,4,FALSE),0) -> 4.2 | F27: Non-preferred vendor: review sourcing, pricing, and conversion to preferred status.
A28: VoltPro Electrical | B28: =IFERROR(VLOOKUP(A28,'Vendor Master'!$A$2:$D$11,3,FALSE),"") -> Yes | C28: =SUMIF('Maintenance Spend Data'!$G$2:$G$55,A28,'Maintenance Spend Data'!$N$2:$N$55) -> 95650 | D28: =SUMIF('Maintenance Spend Data'!$G$2:$G$55,A28,'Maintenance Spend Data'!$U$2:$U$55) -> 7096.2 | E28: =IFERROR(VLOOKUP(A28,'Vendor Master'!$A$2:$D$11,4,FALSE),0) -> 4.7 | F28: Maintain preferred relationship; monitor cost and service performance.
A31: Executive Recommendations
A33: Priority | B33: Opportunity | C33: Recommended Action | D33: Expected Impact
A34: 1 | B34: Preventable Emergencies | C34: Strengthen PM cadence and root-cause reviews | E34: $10.02k
A35: 2 | B35: Budget Overrun Controls | C35: Review quote-to-invoice variances and approvals | E35: $9.3k
A36: 3 | B36: Preventive Optimization | C36: Revies scope, frequency and pricing | E36: $7.1k

Sheet Vendor Master
A1: Vendor Name | B1: Primary Service Category | C1: Preferred Vendor | D1: Rating | E1: Status | F1: Contract Expiration | G1: Insurance Expiration | H1: Source
A2: AllPro Building Services | B2: General Contractor | C2: Yes | D2: 4.3 | E2: Active | F2: 46477 | G2: 46644 | H2: Portfolio Notion master data (synthetic)
A3: BlueSky HVAC Services | B3: HVAC | C3: Yes | D3: 4.8 | E3: Active | F3: 46752 | G3: 46477 | H3: Portfolio Notion master data (synthetic)
A4: ClearPath Janitorial | B4: Cleaning | C4: No | D4: 4.1 | E4: Active | F4: 46568 | G4: 46356 | H4: Portfolio Notion master data (synthetic)
A5: Evergreen Grounds | B5: Landscaping | C5: Yes | D5: 4.5 | E5: Active | F5: 46752 | G5: 46446 | H5: Portfolio Notion master data (synthetic)
A6: PrimeLift Elevator Co. | B6: Elevator | C6: Yes | D6: 4.4 | E6: Active | F6: 46340 | G6: 46387 | H6: Portfolio Notion master data (synthetic)
A7: RapidFlow Plumbing | B7: Plumbing | C7: Yes | D7: 4.6 | E7: Active | F7: 46477 | G7: 46402 | H7: Portfolio Notion master data (synthetic)
A8: SafeGuard Fire Systems | B8: Fire & Life Safety | C8: Yes | D8: 4.9 | E8: Active | F8: 46387 | G8: 46609 | H8: Portfolio Notion master data (synthetic)
A9: Shield Pest Solutions | B9: Pest Control | C9: Yes | D9: 4.6 | E9: Active | F9: 46568 | G9: 46495 | H9: Portfolio Notion master data (synthetic)
A10: Summit Roofing Group | B10: Roofing | C10: No | D10: 4.2 | E10: Pending Review | F10: 46477 | G10: 46539 | H10: Portfolio Notion master data (synthetic)
A11: VoltPro Electrical | B11: Electrical | C11: Yes | D11: 4.7 | E11: Active | F11: 46752 | G11: 46527 | H11: Portfolio Notion master data (synthetic)

Sheet Property Master
A1: Property ID | B1: Property Name | C1: Property Type | D1: City | E1: State | F1: Units | G1: Square Feet | H1: Annual Maintenance Budget ($) | I1: Status | J1: Property Manager | K1: Source
A2: 1 | B2: Lakeview Residences | C2: Multifamily | D2: Orlando | E2: FL | F2: 148 | G2: 168000 | H2: 285000 | I2: Active | J2: Elena Brooks | K2: Portfolio Notion master data (synthetic)
A3: 2 | B3: Cypress Office Center | C3: Office | D3: Tampa | E3: FL | F3: 0 | G3: 92000 | H3: 196000 | I3: Active | J3: Marcus Lee | K3: Portfolio Notion master data (synthetic)
A4: 3 | B4: Sunset Retail Plaza | C4: Retail | D4: Kissimmee | E4: FL | F4: 22 | G4: 76000 | H4: 172000 | I4: Active | J4: Priya Shah | K4: Portfolio Notion master data (synthetic)
A5: 4 | B5: Harbor Point Apartments | C5: Multifamily | D5: Clearwater | E5: FL | F5: 204 | G5: 231000 | H5: 348000 | I5: Active | J5: Daniel Ortiz | K5: Portfolio Notion master data (synthetic)
A6: 5 | B6: Magnolia Mixed Use | C6: Mixed Use | D6: Winter Garden | E6: FL | F6: 64 | G6: 124000 | H6: 238000 | I6: Under Renovation | J6: Sofia Turner | K6: Portfolio Notion master data (synthetic)
A7: 6 | B7: Pinecrest Business Park | C7: Office | D7: Lakeland | E7: FL | F7: 0 | G7: 111000 | H7: 214000 | I7: Active | J7: Aaron Mitchell | K7: Portfolio Notion master data (synthetic)

Sheet Assumptions
A1: Model / Analysis Assumption | B1: Value | C1: Purpose / Rationale | D1: Source
A2: Analysis Start | B2: 46023 | C2: Start of the portfolio analysis period. | D2: Portfolio modeling assumption
A3: Analysis End | B3: 46203 | C3: End of the portfolio analysis period. | D3: Portfolio modeling assumption
A4: Analysis Months | B4: 6 | C4: Used to prorate annual property maintenance budgets. | D4: Derived from analysis period
A6: Savings Driver | B6: Savings Rate | C6: Use | D6: Source
A7: Preventable Emergency | B7: 0.2 | C7: Estimated avoidable portion of emergency maintenance through stronger PM. | D7: Portfolio modeling assumption
A8: Non-Preferred Vendor | B8: 0.08 | C8: Estimated sourcing / negotiated-rate opportunity. | D8: Portfolio modeling assumption
A9: Vendor Consolidation | B9: 0.05 | C9: Estimated portfolio-wide bundling opportunity for recurring services. | D9: Portfolio modeling assumption
A10: Preventive Optimization | B10: 0.1 | C10: Estimated opportunity from optimizing preventive scope/frequency. | D10: Portfolio modeling assumption
A11: Budget Overrun Review | B11: 0.06 | C11: Estimated recovery / negotiation opportunity on material overruns. | D11: Portfolio modeling assumption
A12: None | B12: 0 | C12: No immediate quantified opportunity assigned. | D12: Portfolio modeling assumption

Sheet Data Dictionary
A1: Field | B1: Sheet | C1: Definition
A2: Expense ID | B2: Maintenance Spend Data | C2: Unique synthetic maintenance expense identifier.
A3: Expense Date | B3: Maintenance Spend Data | C3: Date the cost was incurred or recorded.
A4: Property ID | B4: Maintenance Spend Data | C4: Property key linked to Property Master.
A5: Property Name | B5: Maintenance Spend Data | C5: Formula-driven lookup from Property Master.
A6: Property Type | B6: Maintenance Spend Data | C6: Formula-driven lookup from Property Master.
A7: Vendor | B7: Maintenance Spend Data | C7: Service provider associated with the maintenance expense.
A8: Service Category | B8: Maintenance Spend Data | C8: Formula-driven vendor service category.
A9: Preferred Vendor | B9: Maintenance Spend Data | C9: Formula-driven preferred vendor indicator.
A10: Vendor Rating | B10: Maintenance Spend Data | C10: Formula-driven vendor rating from Vendor Master.
A11: Maintenance Type | B11: Maintenance Spend Data | C11: Preventive, Corrective, or Emergency.
A12: Priority | B12: Maintenance Spend Data | C12: Medium, High, or Critical priority.
... A25: Savings Opportunities | B25: Savings Opportunities | C25: Portfolio opportunity summary by savings driver and vendor.

Sheet Hoja1
